ezui/__init__.py
ezui/ezui.py
ezui-0.1.1.dist-info/METADATA
ezui-0.1.1.dist-info/WHEEL
ezui-0.1.1.dist-info/top_level.txt
ezui-0.1.1.dist-info/RECORD
