Metadata-Version: 2.1
Name: ezui
Version: 0.1.1
Summary: A powerful and user-friendly Python library for creating dynamic command-line user interfaces.
Home-page: https://github.com/Plunder283/ezui
Author: Plunder283
Author-email: plunder283@protonmail.com
Keywords: ui,user interface,interface,GUI
Requires: colorama
Requires: keyboard
